unihra/__init__.py
unihra/__main__.py
unihra/client.py
unihra/exceptions.py
unihra/py.typed
unihra-1.2.0.dist-info/METADATA
unihra-1.2.0.dist-info/WHEEL
unihra-1.2.0.dist-info/licenses/LICENSE
unihra-1.2.0.dist-info/RECORD
