Metadata-Version: 2.4
Name: unihra
Version: 1.2.0
Summary: Official Python Client for Unihra API
License: MIT
License-File: LICENSE
Keywords: unihra,seo,api,sdk
Author: Unihra Team
Author-email: dev@unihra.ru
Requires-Python: >=3.8,<4.0
Classifier: License :: OSI Approved :: MIT License
Classifier: Programming Language :: Python :: 3
Classifier: Programming Language :: Python :: 3.8
Classifier: Programming Language :: Python :: 3.9
Classifier: Programming Language :: Python :: 3.10
Classifier: Programming Language :: Python :: 3.11
Classifier: Programming Language :: Python :: 3.12
Classifier: Programming Language :: Python :: 3.13
Classifier: Programming Language :: Python :: 3.14
Requires-Dist: requests (>=2.31.0,<3.0.0)
Project-URL: Homepage, https://unihra.ru
Project-URL: Repository, https://github.com/Unihra/unihra_sdk
